[
  {
    "starttime": "00:06",
    "artist": "Sergej Prokofjev",
    "title": "Sonate in c voor cello en piano op.119: 2.Moderato",
    "time": "0:04:41",
    "composer": "Michal Kanka (cello) Jaromir Klepac (piano)",
    "label": "Praga 250195"
  },
  {
    "starttime": "00:10",
    "artist": "Mychael Danna",
    "title": "Monsoon Wedding (Suite)",
    "time": "0:03:11",
    "composer": "Brussels Philharmonic o.l.v. Dirk Brossé",
    "label": "Silva Screen Records "
  },
  {
    "starttime": "00:14",
    "artist": "Joseph Haydn",
    "title": "Strijkkwartet in G op.77 nr.1: 1.Allegro moderato",
    "time": "0:07:17",
    "composer": "Quatuor Mosaïques",
    "label": "Astree 8799"
  },
  {
    "starttime": "00:21",
    "artist": "Orlandus Lassus",
    "title": "Vivo sol di speranza",
    "time": "0:02:00",
    "composer": "Ratas del viejo Mundo o.l.v. Floris De Rycker",
    "label": "Ramée 1808"
  },
  {
    "starttime": "00:23",
    "artist": "Robert de Visée",
    "title": "Sarabande in b",
    "time": "0:03:18",
    "composer": "Rolf Lislevand (theorbe)",
    "label": "ECM New series 2288-481 1716"
  },
  {
    "starttime": "00:26",
    "artist": "John Dowland",
    "title": "I saw my lady weep",
    "time": "0:05:52",
    "composer": "Paul Agnew (ltenor) Alain Buet (bas) Thomas Dunford (luit)",
    "label": "Alpha 187"
  },
  {
    "starttime": "00:32",
    "artist": "Clara Schumann",
    "title": "Sonate in g voor piano: 4.Rondo",
    "time": "0:05:09",
    "composer": "Isata Kanneh-Mason (piano)",
    "label": "Decca 485 0020"
  },
  {
    "starttime": "00:37",
    "artist": "Gustav Mahler",
    "title": "Symfonie nr.2 in c Auferstehung: 2.Andante moderato",
    "time": "0:10:54",
    "composer": "Koninklijk Concertgebouworkest Amsterdam o.l.v. Bernard Haitink",
    "label": "Philips 462537-2"
  },
  {
    "starttime": "00:48",
    "artist": "George Enescu",
    "title": "Prelude en Fuga in C: 1.Prelude",
    "time": "0:08:54",
    "composer": "Luiza Borac (piano)",
    "label": "Avie AV-2081"
  },
  {
    "starttime": "00:57",
    "artist": "Christoph Willibald von Gluck",
    "title": "Orfeo ed Euridice: Dans van de Gelukzalige Geesten",
    "time": "0:03:02",
    "composer": "Pygmalion o.l.v. Raphael Pichon",
    "label": "Harmonia Mundi HMM-902288"
  },
  {
    "starttime": "01:00",
    "artist": "Carl Orff",
    "title": "Carmina Burana: Chramer, gip die varwe mir",
    "time": "0:03:33",
    "composer": "Collegium Vocale Gent; Anima Eterna Brugge o.l.v. Jos van Immerseel",
    "label": "Zig Zag 353"
  },
  {
    "starttime": "01:04",
    "artist": "Antonio Vivaldi",
    "title": "Tito Manlio RV778: Ti lascerei, gl'affetti miei",
    "time": "0:05:34",
    "composer": "Karina Gauvin (sopraan) Accademia Bizantina o.l.v. Ottavio Dantone",
    "label": "Naïve OP30413"
  },
  {
    "starttime": "01:09",
    "artist": "Wolfgang Amadeus Mozart",
    "title": "Fluitkwartet in D KV285",
    "time": "0:14:08",
    "composer": "Barthold Kuijken (fluit) Sigiswald Kuijken (viool) Lucy van Dael (altviool) Wieland Kuijken (cello)",
    "label": "Accent ACC-48225"
  },
  {
    "starttime": "01:23",
    "artist": "Peteris Vasks",
    "title": "Concerto voor hobo en orkest: 1.Ochtendpastorale",
    "time": "0:06:59",
    "composer": "Albrecht Mayer (hobo) Nationaal Symfonisch Orkest Van Letland o.l.v. Andris Poga",
    "label": "Ondine ODE 1355-2"
  },
  {
    "starttime": "01:30",
    "artist": "John Lunn",
    "title": "Downton Abbey: Emancipation",
    "time": "0:02:15",
    "composer": "Chamber Orchestra Of London o.l.v. Alastair King",
    "label": "Universal 2781146"
  },
  {
    "starttime": "01:33",
    "artist": "Carl Nielsen",
    "title": "Blaaskwintet op.43: 1.Allegro ben moderato",
    "time": "0:08:02",
    "composer": "Les Vents Français",
    "label": "Warner Classics 0190295548704"
  },
  {
    "starttime": "01:41",
    "artist": "Gioacchino Rossini",
    "title": "Il Barbiere di Siviglia: Una voce poco fa",
    "time": "0:06:34",
    "composer": "Diana Damrau (sopraan) Münchner Rundfunkorchester o.l.v. Dan Ettinger",
    "label": "Virgin 519313-2"
  },
  {
    "starttime": "01:47",
    "artist": "Joseph Bodin de Boismortier",
    "title": "Sonate nr.4 in e voor fluit en klavecimbel",
    "time": "0:10:00",
    "composer": "Frank Theuns (traverso) Ewald Demeyere (klavecimbel)",
    "label": "Accent 24168"
  },
  {
    "starttime": "01:57",
    "artist": "Antonio Vivaldi",
    "title": "La Griselda: Ombre vane, ingiusti orrori",
    "time": "0:06:27",
    "composer": "Roberta Invernizzi (sopraan) La Risonanza o.l.v. Fabio Bonizzoni",
    "label": "Glossa 922901"
  },
  {
    "starttime": "02:04",
    "artist": "Ludwig van Beethoven",
    "title": "Concerto nr.2 in Bes voor piano en orkest op.19: 1.Allegro con brio",
    "time": "0:13:48",
    "composer": "Richard Goode (piano) Budapest Festival Orchestra o.l.v. Ivan Fischer",
    "label": "Nonesuch 7559-79928-3"
  },
  {
    "starttime": "02:18",
    "artist": "Mel Bonis",
    "title": "Sonate in cis voor fluit en piano op.64: 1.Andantino con moto",
    "time": "0:05:00",
    "composer": "Maria Cecilia Muñoz (fluit) Tiffany Butt (piano)",
    "label": "Ars Produktion ARS 38 129"
  },
  {
    "starttime": "02:23",
    "artist": "Luigi Boccherini",
    "title": "Strijkkwintet in d op.18 nr.5",
    "time": "0:18:53",
    "composer": "Ensemble Explorations",
    "label": "Harmonia Mundi 901894"
  },
  {
    "starttime": "02:42",
    "artist": "Ralph Vaughan Williams/ork.Anthony Payne",
    "title": "Four last songs: 2.Tired",
    "time": "0:02:03",
    "composer": "Roderick Williams (bariton) Bergen Philharmonic Orchestra o.l.v. Sir Andrew Davis",
    "label": "Chandos 5186"
  },
  {
    "starttime": "02:44",
    "artist": "Pancho Vladigerov",
    "title": "Fox-Trot",
    "time": "0:03:05",
    "composer": "Klavierduo Genova &amp; Dimitrov",
    "label": "CPO 999 733-2"
  },
  {
    "starttime": "02:47",
    "artist": "Edward Elgar/arr.Percy M. Young",
    "title": "Spanish Lady Suite",
    "time": "0:11:16",
    "composer": "Sinfonia o.l.v. Dirk Vermeulen",
    "label": "Eufoda 12070"
  },
  {
    "starttime": "02:58",
    "artist": "Wolfgang Amadeus Mozart",
    "title": "Divertimento in D KV136: 1.Allegro",
    "time": "0:04:00",
    "composer": "Hagen Quartett",
    "label": "DG 439 940-2"
  },
  {
    "starttime": "03:02",
    "artist": "George Frideric Handel",
    "title": "Theodora HWV68: As with rosy steps the morn",
    "time": "0:07:53",
    "composer": "Lorraine Hunt (mezzosopraan) Barokksolistene o.l.v. Harry Bicket",
    "label": "BIS 1997"
  },
  {
    "starttime": "03:10",
    "artist": "Ludwig van Beethoven",
    "title": "Concerto nr.5 in Es voor piano en orkest op.73 Keizersconcerto: 3.Rondo",
    "time": "0:10:23",
    "composer": "Radu Lupu (piano) Israel Philharmonic Orchestra o.l.v. Zubin Mehta",
    "label": "Decca 400 050-2"
  },
  {
    "starttime": "03:20",
    "artist": "André Caplet",
    "title": "Rêverie et Petite Valse",
    "time": "0:06:55",
    "composer": "Ransom Wilson (dwarsfluit) François Dumont (piano)",
    "label": "Nimbus NI6407"
  },
  {
    "starttime": "03:27",
    "artist": "Charles Koechlin",
    "title": "Quatre Poèmes d'Edmond Haraucourt op.7: 4.Aux Temps des Fées",
    "time": "0:03:37",
    "composer": "Juliane Banse (sopraan) Radio-Sinfonieorchester Stuttgart des SWR o.l.v. Heinz Holliger",
    "label": "Hänssler Classic 93.159"
  },
  {
    "starttime": "03:31",
    "artist": "Trad. Rusland",
    "title": "Chounem (Volkslied uit Rusland)",
    "time": "0:03:10",
    "composer": "Roby Lakatos And His Gipsy Band",
    "label": "Impuls IMP-99367"
  },
  {
    "starttime": "03:34",
    "artist": "Franz Schubert",
    "title": "Winterreise D911: 1.Gute Nacht",
    "time": "0:05:33",
    "composer": "Thomas Bauer (bariton) Jos van Immerseel (pianoforte)",
    "label": "Zig-Zag 101102"
  },
  {
    "starttime": "03:40",
    "artist": "Johann Sebastian Bach",
    "title": "Sonate in A voor traverso en klavecimbel BWV1032",
    "time": "0:12:04",
    "composer": "Barthold Kuijken (traverso) Ewald Demeyere (klavecimbel)",
    "label": "Accent 22150"
  },
  {
    "starttime": "03:52",
    "artist": "Joseph Haydn",
    "title": "Symfonie nr.49 in f La passione",
    "time": "0:19:37",
    "composer": "Les Métamorphoses o.l.v. Raphaël Feye",
    "label": "Evil Penguin Records EPRC 0029"
  },
  {
    "starttime": "04:11",
    "artist": "Johann Georg Reutter",
    "title": "La magnanimita di Alessandro: Venga l'età vetusta",
    "time": "0:06:50",
    "composer": "Monika Mauch (sopraan) Stanislava Jirku (altus) La Gioia Armonica o.l.v. Jürgen Banholzer",
    "label": "Ramée 1302"
  },
  {
    "starttime": "04:18",
    "artist": "Wolfgang Amadeus Mozart",
    "title": "Concerto in A voor klarinet en orkest KV622: 1.Allegro",
    "time": "0:12:36",
    "composer": "Walter Boeykens (klarinet) Prima La Musica o.l.v. Dirk Vermeulen",
    "label": "Etcetera 5261"
  },
  {
    "starttime": "04:31",
    "artist": "Cyril Scott",
    "title": "Water-Wagtail: 3.Bergeronnette",
    "time": "0:02:26",
    "composer": "Nino Gvetadze (piano)",
    "label": "Challenge Classics CC72819"
  },
  {
    "starttime": "04:33",
    "artist": "Carl Stamitz",
    "title": "Kwartet in Bes voor klarinet, viool, altviool en cello op.19 nr.2",
    "time": "0:15:25",
    "composer": "Contrasts Ensemble",
    "label": "Aliud Records ACD HJ-041-2"
  },
  {
    "starttime": "04:49",
    "artist": "Franz Schubert",
    "title": "Im Fruhling D882",
    "time": "0:04:39",
    "composer": "Ian Bostridge (tenor) Julian Drake (piano)",
    "label": "EMI 7243-5 56347 2-6"
  },
  {
    "starttime": "04:53",
    "artist": "Gaspar Sanz",
    "title": "Xacara",
    "time": "0:03:27",
    "composer": "Xavier Diaz (barokgitaar) Pedro Estevan (percussie)",
    "label": "Zig-Zag Territoires 061002"
  },
  {
    "starttime": "04:57",
    "artist": "Francesco Barbella",
    "title": "Concerto nr.3 in C voor blokfluit, strijkers en b.c.",
    "time": "0:10:49",
    "composer": "Maurice Steger (blokfluit) Ensemble",
    "label": "harmonia mundi 902135"
  },
  {
    "starttime": "05:08",
    "artist": "Francis Poulenc",
    "title": "Sinfonietta: 2.Molto vivace",
    "time": "0:05:24",
    "composer": "New London Orchestra o.l.v. Ronald Corp",
    "label": "Helios 55167"
  },
  {
    "starttime": "05:13",
    "artist": "Ralph Vaughan Williams",
    "title": "English Folk Song Suite",
    "time": "0:09:04",
    "composer": "Royal Liverpool Philharmonic Orchestra o.l.v. John Wilson",
    "label": "Avie 2194"
  },
  {
    "starttime": "05:22",
    "artist": "Gioacchino Rossini",
    "title": "Sonata a quattro nr.1 in G",
    "time": "0:12:05",
    "composer": "Ensemble Explorations o.l.v. Roel Dieltiens",
    "label": "Harmonia mundi 901776"
  },
  {
    "starttime": "05:34",
    "artist": "Luise Adolpha Le Beau",
    "title": "Sonate in D voor piano en cello op.17: 1.Allegro molto",
    "time": "0:05:45",
    "composer": "Denis Severin (cello) Tatiana Korsunskaya (piano)",
    "label": "MDG 903 1872-6"
  },
  {
    "starttime": "05:40",
    "artist": "Hugo Wolf",
    "title": "Die Bekehrte",
    "time": "0:03:10",
    "composer": "Christiane Oelze (sopraan) Eric Schneider (piano)",
    "label": "Berlin Classics 1030-2"
  },
  {
    "starttime": "05:43",
    "artist": "Serge Gainsbourg",
    "title": "La Javanaise",
    "time": "0:03:18",
    "composer": "Khatia Buniatishvili (piano)",
    "label": "Sony Classical 886448587323"
  },
  {
    "starttime": "05:47",
    "artist": "Camille Saint-Saëns",
    "title": "Havanaise voor viool en orkest op.83",
    "time": "0:09:40",
    "composer": "Janine Jansen (viool) Royal Philharmonic Orchestra o.l.v. Barry Wordsworth",
    "label": "Decca 475011-2"
  },
  {
    "starttime": "05:56",
    "artist": "Franz Schubert",
    "title": "Symfonie nr.1 in D D82: 4.Allegro vivace",
    "time": "0:05:14",
    "composer": "B'rock Orchestra o.l.v. René Jacobs",
    "label": "Pentatone 82794907076"
  },
  {
    "starttime": "06:02",
    "artist": "Wolfgang Amadeus Mozart",
    "title": "Ouverture Lucio Silla KV135",
    "time": "0:08:15",
    "composer": "London Philharmonic Orchestra o.l.v. Bernard Haitink",
    "label": "Philips 432 512-2"
  },
  {
    "starttime": "06:10",
    "artist": "Anoniem",
    "title": "El Saltarello - Gagliarda El tu tu - Gagliarda La lavandara",
    "time": "0:04:15",
    "composer": "Consort Veneto",
    "label": "Tactus 500001"
  },
  {
    "starttime": "06:14",
    "artist": "Anton Arensky",
    "title": "Scherzo voor piano op.53 nr.2",
    "time": "0:03:07",
    "composer": "Stephen Coombs (piano)",
    "label": "Hyperion 67066"
  },
  {
    "starttime": "06:17",
    "artist": "Peter Tsjaikovski",
    "title": "De Notenkraker op.71: Bloemenwals",
    "time": "0:06:51",
    "composer": "Berliner Philharmoniker o.l.v. Sir Simon Rattle",
    "label": "EMI 6 31621 2"
  },
  {
    "starttime": "06:24",
    "artist": "Ludwig van Beethoven",
    "title": "Sonate nr.4 in a voor viool en piano op.23: 1.Presto",
    "time": "0:07:22",
    "composer": "Daniel Sepec (viool) Andreas Staier (pianoforte)",
    "label": "Harmonia Mundi HMC-901919"
  },
  {
    "starttime": "06:32",
    "artist": "George Frideric Handel",
    "title": "Triosonate in bes voor 2 hobo's en b.c.: 4.Allegro",
    "time": "0:03:31",
    "composer": "Marcel Ponseele (hobo) Ann Vanlancker (hobo) Ewald Demeyere (klavecimbel) Richte van der Meer (cello)",
    "label": "Accent 99136"
  },
  {
    "starttime": "06:35",
    "artist": "Franz Schubert",
    "title": "Pianotrio nr.1 in Bes op.99 D898: 3.Scherzo",
    "time": "0:06:38",
    "composer": "Yuuko Shiokawa (viool) Miklos Perenyi (cello) Andras Schiff (piano)",
    "label": "Teldec 0630-13151-2"
  },
  {
    "starttime": "06:42",
    "artist": "Nicola Piovani",
    "title": "La vita è bella: Thema",
    "time": "0:02:45",
    "composer": "Renaud Capuçon (viool) Brussels Philharmonic o.l.v. Stéphane Denève",
    "label": "Erato 0190295633936"
  },
  {
    "starttime": "06:44",
    "artist": "Benedetto Marcello",
    "title": "Quando penso agl'affanni: Sinfonia",
    "time": "0:06:21",
    "composer": "Accademia Bizantina o.l.v. Ottavio Dantone",
    "label": "Decca 470630-2"
  },
  {
    "starttime": "06:51",
    "artist": "Joseph Haydn",
    "title": "Pianotrio nr.21 in C: 2.Molto andante",
    "time": "0:04:07",
    "composer": "Trio Fontenay",
    "label": "Teldec 0630-15857-2"
  },
  {
    "starttime": "06:55",
    "artist": "Johann Sebastian Bach",
    "title": "Suite nr.3 in D voor orkest BWV1068: 3.Gavotte I&amp;II",
    "time": "0:04:10",
    "composer": "Il Fondamento o.l.v. Paul Dombrecht",
    "label": "Fuga Libera 580"
  },
  {
    "starttime": "07:03",
    "artist": "Ludwig van Beethoven",
    "title": "Sonate nr.5 in F voor viool en piano op.24 Frühlingssonate: 1.Allegro",
    "time": "0:09:37",
    "composer": "Augustin Dumay (viool) Maria João Pires (piano)",
    "label": "DG 471495-2"
  },
  {
    "starttime": "07:13",
    "artist": "Robert Schumann",
    "title": "Myrthen op.25: 3.Der Nussbaum",
    "time": "0:03:08",
    "composer": "Bryn Terfel (bas-bariton) Malcolm Martineau (piano)",
    "label": "Deutsche Grammophon 447 042-2"
  },
  {
    "starttime": "07:17",
    "artist": "Gabriel Pierné",
    "title": "Canzonetta op.19 (arr.)",
    "time": "0:03:37",
    "composer": "Annelien Van Wauwe (klarinet) Orchestre National de Lille o.l.v. Alexandre Bloch",
    "label": "PentaTone classics PTC5186808"
  },
  {
    "starttime": "07:20",
    "artist": "Felix Mendelssohn",
    "title": "Strijkkwartet nr.1 in Es op.12: 2.Canzonetta",
    "time": "0:04:13",
    "composer": "Neues Leipziger Streichquartett",
    "label": "MDG 3071055-2"
  },
  {
    "starttime": "07:25",
    "artist": "Frank Bridge",
    "title": "Suite voor Strijkers: 2.Intermezzo",
    "time": "0:03:24",
    "composer": "Britten Sinfonia o.l.v. Nicholas Cleobury",
    "label": "Conifer 75605-51327-2"
  },
  {
    "starttime": "07:33",
    "artist": "Anoniem",
    "title": "El Saltarello - Gagliarda El tu tu - Gagliarda La lavandara",
    "time": "0:04:15",
    "composer": "Consort Veneto",
    "label": "Tactus 500001"
  },
  {
    "starttime": "07:37",
    "artist": "Adriaan Willaert",
    "title": "Canzone Villanesche alla Napolitano: A Quand'a quand'havea una vicina",
    "time": "0:02:26",
    "composer": "Dionysos Now!",
    "label": "Evil Penguin Classic EPRC-0043"
  },
  {
    "starttime": "07:40",
    "artist": "Enrico Cannio",
    "title": "'A serenata 'e Pullecenella",
    "time": "0:02:46",
    "composer": "Bel Ayre",
    "label": "Bel Ayre "
  },
  {
    "starttime": "07:53",
    "artist": "Florence Price",
    "title": "Symfonie nr.3 in c: 3.Juba",
    "time": "0:05:00",
    "composer": "Philadelphia Orchestra o.l.v. Yannick Nézet-Séguin",
    "label": "Deutsche Grammophon 4862029"
  },
  {
    "starttime": "08:08",
    "artist": "George Brassens",
    "title": "Supplique pour être enterré sur la plage de Sète",
    "time": "0:02:44",
    "composer": "Rodolphe Raffalli (gitaar) Doudou Cuillerier (gitaar) Max Robin (gitaar) Antonio Licusati (contrabas)",
    "label": "Frémeaux &amp; Associés FA-5092"
  },
  {
    "starttime": "08:11",
    "artist": "Jacques Prévert, Joseph Kosma",
    "title": "Les feuilles mortes",
    "time": "0:03:22",
    "composer": "Yves Montand",
    "label": "Le chant du monde 574 2081"
  },
  {
    "starttime": "08:14",
    "artist": "Henrique Oswald",
    "title": "Valse lente",
    "time": "0:03:01",
    "composer": "Nelson Freire (piano)",
    "label": "Decca 478 3533"
  },
  {
    "starttime": "08:17",
    "artist": "Heitor Villa-Lobos",
    "title": "Vijf Preludes voor gitaar: nr.2 in E",
    "time": "0:03:53",
    "composer": "Krzysztof Meisinger (gitaar)",
    "label": "Fuga Libera 599"
  },
  {
    "starttime": "08:22",
    "artist": "Edvard Grieg",
    "title": "4 Noorse dansen op.35: 3.Allegro moderato alla marcia",
    "time": "0:03:42",
    "composer": "Bergen Philharmonic Orchestra o.l.v. Ole Kristian Ruud",
    "label": "BIS 1291"
  },
  {
    "starttime": "08:26",
    "artist": "Antonin Dvorak",
    "title": "Slavische dansen op.46: nr.4 in F",
    "time": "0:06:05",
    "composer": "Budapest Festival Orchestra o.l.v. Ivan Fischer",
    "label": "Channel 90210"
  },
  {
    "starttime": "08:33",
    "artist": "Jean-Marie Leclair",
    "title": "Concerto in D voor viool, strijkers en b.c. op.10 nr.3: 3.Allegro ma non troppo",
    "time": "0:05:11",
    "composer": "Théotime Langlois de Swarte (viool) Les Ombres",
    "label": "Harmonia Mundi HMM-902649"
  },
  {
    "starttime": "08:39",
    "artist": "Michel-Richard Delalande",
    "title": "Miserere: nrs.1-6",
    "time": "0:11:35",
    "composer": "Ensemble Correspondances o.l.v. Sébastien Daucé",
    "label": "Harmonia Mundi HMM-902625"
  },
  {
    "starttime": "08:51",
    "artist": "Carl Friedrich Abel",
    "title": "Interludium in D",
    "time": "0:02:22",
    "composer": "Hille Perl (gamba)",
    "label": "deutsche harmonia mundi 88697824002"
  },
  {
    "starttime": "08:53",
    "artist": "Johann Sebastian Bach",
    "title": "Das Wohltemperierte Klavier boek 1: Prelude en fuga nr.23 in B BWV868",
    "time": "0:03:03",
    "composer": "Julien Libeer (piano)",
    "label": "Harmonia Mundi HMM-902696.97"
  },
  {
    "starttime": "08:57",
    "artist": "Josef Myslivecek",
    "title": "Kwintet nr.4 in B voor blazers",
    "time": "0:05:54",
    "composer": "L'Orfeo Bläserensemble o.l.v. Carin van Heerden",
    "label": "CPO 777377-2"
  },
  {
    "starttime": "09:10",
    "artist": "Willie The Lion Smith",
    "title": "Echo of Spring",
    "time": "0:04:15",
    "composer": "Mike Strickland (piano)",
    "label": "MSP Records "
  },
  {
    "starttime": "09:15",
    "artist": "Aaron Copland",
    "title": "Twelve Poems of Emily Dickinson: Nature, the Gentlest Mother",
    "time": "0:04:03",
    "composer": "Joyce DiDonato (mezzosopraan/coloratuur) Il Pomo d'Oro o.l.v. Maxim Emelyanychev",
    "label": "Erato 0190296465154"
  },
  {
    "starttime": "09:19",
    "artist": "Edvard Grieg",
    "title": "Peer Gynt Suite nr.1 op.46: 1.Morgenstemming",
    "time": "0:04:15",
    "composer": "Oslo Philharmonic Orchestra o.l.v. Esa-Pekka Salonen",
    "label": "Sony 44528"
  },
  {
    "starttime": "09:23",
    "artist": "Edvard Grieg",
    "title": "Peer Gynt Suite nr.1 op.46: 2.Ases dood",
    "time": "0:05:40",
    "composer": "Oslo Philharmonic Orchestra o.l.v. Esa-Pekka Salonen",
    "label": "Sony 44528"
  },
  {
    "starttime": "09:29",
    "artist": "Edvard Grieg",
    "title": "Peer Gynt Suite nr.1 op.46: 3.Anitra's dans",
    "time": "0:03:16",
    "composer": "Oslo Philharmonic Orchestra o.l.v. Esa-Pekka Salonen",
    "label": "Sony 44528"
  },
  {
    "starttime": "09:42",
    "artist": "Franz Schubert",
    "title": "Allegretto in c D915",
    "time": "0:05:14",
    "composer": "Maurizio Pollini (piano)",
    "label": "DG 427 326-2"
  },
  {
    "starttime": "09:47",
    "artist": "Eduard Lassen",
    "title": "Immer bei dir op.68 nr.1",
    "time": "0:02:10",
    "composer": "Reinoud Van Mechelen (tenor) Anthony Romaniuk (piano)",
    "label": "Musique en Wallonie MEW-2099"
  },
  {
    "starttime": "09:50",
    "artist": "Felix Mendelssohn",
    "title": "Symfonie nr.2 in Bes op.52 Lobgesang: 2.Allegretto un poco agitato",
    "time": "0:07:00",
    "composer": "London Symphony Orchestra o.l.v. Claudio Abbado",
    "label": "DG 415353-2"
  },
  {
    "starttime": "09:57",
    "artist": "Joseph Haydn",
    "title": "Strijkkwartet in Es op.20 nr.1: 1.Allegro moderato",
    "time": "0:05:51",
    "composer": "Hagen Quartett",
    "label": "DG 439920-2"
  },
  {
    "starttime": "10:09",
    "artist": "Franz Schubert",
    "title": "Pianokwintet in A groot, op. posth. 114 D 667 (voor piano, viool, altviool, cello en contrabas) /Die Forelle/Forellenkwintet: III Scherzo. Presto",
    "time": "0:04:23",
    "composer": "Jörg Demus (pianoforte) Thomas Albertus Irnberger (viool) Martin Ortner (altviool) Heidi Litschauer (cello) Brita Bürgschwendtner (contrabas)",
    "label": "Gramola 98919"
  },
  {
    "starttime": "10:18",
    "artist": "Ludwig Van Beethoven",
    "title": "Symfonie nr. 6 in F groot, op. 68 /Pastorale: I Erwachen heiterer Empfindungen bei der Ankunft auf dem Lande - Allegro..",
    "time": "0:08:51",
    "composer": "Berliner Philharmoniker o.l.v. Herbert von Karajan",
    "label": "Deutsche Grammophon 453 701-2"
  },
  {
    "starttime": "10:31",
    "artist": "Sergei Prokofiev",
    "title": "Concerto voor piano en orkest nr. 2 in g klein, op. 16: I Andantino",
    "time": "0:10:51",
    "composer": "Laura Mikkola (piano) Orchestre Philharmonique De Liège o.l.v. Pierre Bartholomee",
    "label": ""
  },
  {
    "starttime": "10:46",
    "artist": "Joseph-Hector Fiocco",
    "title": "Homo Quidam (voor sopraan, koor en orkest): I Homo Quidam",
    "time": "0:04:22",
    "composer": "Collegium Instrumentale Brugense Capella Brugensis o.l.v. Patrick Peire",
    "label": "Naxos 8.557120"
  },
  {
    "starttime": "10:54",
    "artist": "Eric Whitacre",
    "title": "Deep Field: Earth Choir",
    "time": "0:04:49",
    "composer": "Eric Whitacre Singers &amp; Virtual Choir 5 (koor) Royal Philharmonic Orchestra o.l.v. Eric Whitacre",
    "label": "Unquiet UNQ011"
  },
  {
    "starttime": "11:02",
    "artist": "César Franck",
    "title": "Prelude, fuga en variatie, op. 18 (à son ami Monsieur Camille Saint-Saens) /Prélude, fugue et variation (uit \"Six Pièces\"): I Prélude",
    "time": "0:03:44",
    "composer": "Alexis Weissenberg (piano)",
    "label": "EMI Classics 7243-5 85837 2-4"
  },
  {
    "starttime": "11:10",
    "artist": "Karel Goeyvaerts",
    "title": "Aquarius - Tango (with a generous and a sophisticated elegance)",
    "time": "0:01:52",
    "composer": "Jan Michiels (piano)",
    "label": "Megadisc MDC-7848"
  },
  {
    "starttime": "11:15",
    "artist": "Frédéric Chopin",
    "title": "12 études, op. 10: Etude in c klein, op. 10 nr. 12 /Revolutionaire/De Val van Warschau",
    "time": "0:03:02",
    "composer": "Frederic Chiu (piano)",
    "label": "Harmonia Mundi HMU-907201"
  },
  {
    "starttime": "11:22",
    "artist": "Guillaume Lekeu",
    "title": "Pianokwartet: II Lent et passionné",
    "time": "0:10:38",
    "composer": "Jan Michiels (piano) Elisa Kawaguti (viool) Leo De Neve (altviool) Jan Sciffer (cello) Spiegel Kwartet",
    "label": "MDG 644 1266-2"
  },
  {
    "starttime": "11:36",
    "artist": "Wolfgang Amadeus Mozart",
    "title": "Don Giovanni, KV 527: Madamina, il catalogo è questo /Cataloog-aria",
    "time": "0:05:43",
    "composer": "Thomas Quasthoff (bariton) Wurttembergisches Kammerorchester Heilbronn",
    "label": "RCA Victor 09026-61428-2"
  },
  {
    "starttime": "11:46",
    "artist": "Felix Mendelssohn Bartholdy",
    "title": "Symfonie nr. 4 in A groot, op. 90 /Italiaanse symfonie: IV Saltarello: Presto",
    "time": "0:05:31",
    "composer": "London Symphony Orchestra o.l.v. Claudio Abbado",
    "label": "Deutsche Grammophon 415 353-2"
  },
  {
    "starttime": "11:56",
    "artist": "Maurice Ravel",
    "title": "Gaspard de la nuit (Trois poèmes pour piano d'après Aloysius Bertrand): I Ondine",
    "time": "0:06:19",
    "composer": "Martha Argerich (piano)",
    "label": "deutsch 453 576-2"
  },
  {
    "starttime": "12:07",
    "artist": "Scott Joplin/arr. Alain Crepin",
    "title": "The Entertainer (arr.)",
    "time": "0:02:53",
    "composer": "Saxofoon Ensemble Brussels Conservatorium",
    "label": "René Gailly 87 170"
  },
  {
    "starttime": "12:11",
    "artist": "Kurt Weill",
    "title": "Marie Galante: 4.Scène au dancing",
    "time": "0:03:06",
    "composer": "Ensemble Dreigroschen o.l.v. Giorgio Bernasconi",
    "label": "Assai 207192"
  },
  {
    "starttime": "12:14",
    "artist": "Koji Kondo/arr.Jelle Tassyns",
    "title": "Super Mario Bros",
    "time": "0:04:53",
    "composer": "Joyce Kuipers (cello)",
    "label": "Arco music "
  },
  {
    "starttime": "12:20",
    "artist": "Armand Coeck",
    "title": "Triptique: III.Rosa Mystica (bewerkt voor cello en twee gitaren)",
    "time": "0:02:56",
    "composer": "Wouter Vercruysse (cello) Joris D'Haene (klassieke gitaar) Gino Herman (klassieke gitaar)",
    "label": "Auurk Records 20080418"
  },
  {
    "starttime": "12:23",
    "artist": "Sandeep Das",
    "title": "If You Shall Return...",
    "time": "0:06:46",
    "composer": "Yo-Yo Ma (cello) Bill Frisell (gitaar) Silk Road Ensemble",
    "label": "Master Classics LC 06868"
  },
  {
    "starttime": "12:30",
    "artist": "Anoniem",
    "title": "Drive the Cold Winter Away",
    "time": "0:04:34",
    "composer": "Nicholas Scott (tenor) Fiona Mcgown (mezzosopraan) Les Musiciens de Saint-Julien o.l.v. François Lazarevitch",
    "label": "Alpha 636"
  },
  {
    "starttime": "12:35",
    "artist": "Diego Ortiz",
    "title": "Recercada segunda sobre el passamezzo moderno",
    "time": "0:02:36",
    "composer": "Joris Van Goethem (blokfluit) Ewald Demeyere (klavecimbel) Philippe Malfeyt (barokgitaar) Chris Joris (percussie)",
    "label": "Opus 111 30272"
  },
  {
    "starttime": "12:37",
    "artist": "David Bruce",
    "title": "Death is a Friend of Ours: 3.Death is a Friend of Ours",
    "time": "0:03:36",
    "composer": "Avi Avital (mandoline) Sean Shibe (gitaar) Ophira Zakai (theorbe) Anneleen Lenaerts (harp) Yizhar Karshon (klavecimbel)",
    "label": "Deutsche Grammophon 4838534"
  },
  {
    "starttime": "12:42",
    "artist": "Gabriel Fauré",
    "title": "Sicilienne voor fluit en harp op.78",
    "time": "0:03:39",
    "composer": "Gaby Pas-Van Riet (fluit) Sophie Hallynck (harp)",
    "label": "Hänssler 93.175"
  },
  {
    "starttime": "12:46",
    "artist": "Cécile Chaminade",
    "title": "Concertino in D voor fluit en orkest op.107",
    "time": "0:07:37",
    "composer": "Magali Mosnier (fluit) Münchner Rundfunkorchester o.l.v. Marco Armiliato",
    "label": "Sony Classical 82876-76516-2"
  },
  {
    "starttime": "12:54",
    "artist": "Johann Christian Bach",
    "title": "Sonate in A op.17 nr.5",
    "time": "0:06:14",
    "composer": "Daniil Trifonov (piano)",
    "label": "Deutsche Grammophon 4838530"
  },
  {
    "starttime": "13:07",
    "artist": "Carlos Gardel",
    "title": "Scent of a Woman: Por Una Cabeza",
    "time": "0:02:12",
    "composer": "The Tango Project",
    "label": "MCA MCD-10759"
  },
  {
    "starttime": "13:09",
    "artist": "Pedro Rodrigues",
    "title": "Carnaval de Sao Vicente",
    "time": "0:05:14",
    "composer": "Anat Cohen (klarinet) Anzic Orchestra",
    "label": "Anzic Records "
  },
  {
    "starttime": "13:15",
    "artist": "Jan Van Der Roost",
    "title": "Rikudim",
    "time": "0:09:01",
    "composer": "Walter Boeykens Clarinet Choir o.l.v. Walter Boeykens",
    "label": "De Haske Records 14.001"
  },
  {
    "starttime": "13:25",
    "artist": "Nikolaj Rimski-Korsakov",
    "title": "De vlucht van de hommel",
    "time": "0:01:01",
    "composer": "Sharon Bezaly (fluit) Residentie-Orkest Den Haag o.l.v. Neeme Järvi",
    "label": "BIS 1679"
  },
  {
    "starttime": "13:26",
    "artist": "Peter Tsjaikovski",
    "title": "Concerto in D voor viool en orkest op.35: 3.Finale",
    "time": "0:10:37",
    "composer": "Yossif Ivanov (viool) Brussels Philharmonic o.l.v. Damian Iorio",
    "label": "Warner Classics 0190296416514"
  },
  {
    "starttime": "13:37",
    "artist": "Eduardo Rovira",
    "title": "Tango para Ángele",
    "time": "0:04:37",
    "composer": "Stephen Meyer (viool) Ivo De Greef (piano) Camilo Cordoba (gitaar) Ariel Eberstein (contrabas) Lysandre Donoso (bandoneon) Sonico",
    "label": "Eigen Beheer "
  },
  {
    "starttime": "13:42",
    "artist": "Mario Claudio/Ricardo J. Dias",
    "title": "Se Fores, Nao Chores por Mim",
    "time": "0:03:53",
    "composer": "Cristina Branco (zang) Ricardo J. Dias (piano) Bernardo Couto (Portugese gitaar) Fernando Maia (contrabas)",
    "label": "Universal Digital"
  },
  {
    "starttime": "13:46",
    "artist": "Sophie Cavez",
    "title": "Tamara",
    "time": "0:03:01",
    "composer": "Sophie Cavez (accordeon) Baltazar Montanaro (viool)",
    "label": "Appel Rekords "
  },
  {
    "starttime": "13:49",
    "artist": "Roland Dyens",
    "title": "Lettre à la Seine",
    "time": "0:01:38",
    "composer": "Enno Voorhorst (klassieke gitaar)",
    "label": "Cobra records 0066"
  },
  {
    "starttime": "13:51",
    "artist": "Márcio Faraco",
    "title": "Paris",
    "time": "0:03:20",
    "composer": "Márcio Faraco",
    "label": "World Village WVF479100"
  },
  {
    "starttime": "13:55",
    "artist": "Erik Satie",
    "title": "Je te veux",
    "time": "0:05:07",
    "composer": "Anne Queffélec (piano)",
    "label": "Warner 5054197949258"
  },
  {
    "starttime": "14:03",
    "artist": "Stefano Landi",
    "title": "Superbe colli",
    "time": "0:06:23",
    "composer": "Harry van der Kamp (bas) Tragicomedia o.l.v. Stephen Stubbs",
    "label": "Teldec 4509-98410-2"
  },
  {
    "starttime": "14:11",
    "artist": "Giacomo Carissimi",
    "title": "Vanitas vanitatum",
    "time": "0:17:15",
    "composer": "Barbara Borden (sopraan) Suzie Le Blanc (sopraan) Stephanie Möller (sopraan) Steve Dugardin (alt) John Elwes (tenor) Harry van der Kamp (bas) Stephen Stubbs (aartsluit/barokgitaar) Erin Headley (lirone/gamba) Tragicomedia o.l.v. Stephen Stubbs",
    "label": "WEA/Warner Classics/Teldec 4509-98410-2"
  },
  {
    "starttime": "14:29",
    "artist": "Fanny Mendelssohn",
    "title": "Villa Medicis",
    "time": "0:06:03",
    "composer": "Alfredo Ovalles (piano)",
    "label": "Gramola GRAM-99094"
  },
  {
    "starttime": "14:36",
    "artist": "Charles Gounod",
    "title": "Faust: Oh! Dieu! que de bijoux! ... Ah! Je ris de me voir si belle (Air des bijoux)",
    "time": "0:04:55",
    "composer": "Angela Gheorghiu (sopraan) Orchestra del Teatro Regio di Torino; Coro del Teatro Regio Di Torino o.l.v. John Mauceri",
    "label": "Decca 478 9679"
  },
  {
    "starttime": "14:42",
    "artist": "Franz Liszt",
    "title": "Eine Faust-Symphonie",
    "time": "1:16:44",
    "composer": "Kenneth Riegel (tenor) Boston Symphony Orchestra; Tanglewood Festival Chorus o.l.v. Leonard Bernstein",
    "label": "Deutsche Grammophon 447 449-2"
  },
  {
    "starttime": "16:00",
    "artist": "Felix Mendelssohn",
    "title": "Lieder ohne Worte op.30 (Boek 2)",
    "time": "0:17:01",
    "composer": "Amir Katz (piano)",
    "label": "Live Classics LCL-807"
  },
  {
    "starttime": "16:04",
    "artist": "Anoniem/arr.Erik Van nevel",
    "title": "Tota pulchra es",
    "time": "0:04:05",
    "composer": "Currende o.l.v. Erik Van Nevel",
    "label": "Etcetera KTC-1711"
  },
  {
    "starttime": "16:09",
    "artist": "Clara Schumann",
    "title": "Liebst du um Schönheit",
    "time": "0:02:31",
    "composer": "Barbara Bonney (sopraan) Vladimir Ashkenazy (piano)",
    "label": "Decca 452 898-2"
  },
  {
    "starttime": "16:12",
    "artist": "Clara Schumann",
    "title": "6 Lieder op.13: 2.Sie liebten sich beide-1.Ich stand in dunklen Träumen",
    "time": "0:03:49",
    "composer": "Barbara Bonney (sopraan) Vladimir Ashkenazy (piano)",
    "label": "Decca 452 898-2"
  },
  {
    "starttime": "16:17",
    "artist": "Ralph Vaughan Williams",
    "title": "Vijf variaties op Dives and Lazarus voor strijkers en harp",
    "time": "0:11:58",
    "composer": "Royal Liverpool Philharmonic Orchestra o.l.v. Andrew Manze",
    "label": "Onyx 4214"
  },
  {
    "starttime": "16:18",
    "artist": "Felix Mendelssohn/arr.Bernd Stegmann",
    "title": "Ach, wie flüchtig, ach, wie nichtig (arr. Lied ohne Worte op.30 nr.2)",
    "time": "0:02:17",
    "composer": "Stefan Göttelmann (orgel) Berliner Vokalensemble o.l.v. Bernd Stegmann",
    "label": "Carus 97.050-99"
  },
  {
    "starttime": "16:21",
    "artist": "Johann Sebastian Bach",
    "title": "Cantate BWV26 Ach wie flüchtig, ach wie nichtig",
    "time": "0:14:41",
    "composer": "Yukari Nonoshita (sopraan) Robin Blaze (altus) Makoto Sakurada (tenor) Peter Kooij (bas) Bach Collegium Japan o.l.v. Masaaki Suzuki",
    "label": "BIS 1451"
  },
  {
    "starttime": "16:30",
    "artist": "Felix Mendelssohn",
    "title": "Erntelied op.8 nr.4",
    "time": "0:04:40",
    "composer": "Dietrich Fischer-Dieskau (bariton) Gerald Moore (piano)",
    "label": "EMI 3 91990 2"
  },
  {
    "starttime": "16:35",
    "artist": "Jennifer Higdon",
    "title": "String Poetic",
    "time": "0:20:32",
    "composer": "Jennifer Koh (viool) Reiko Uchida (piano)",
    "label": "Cedille Records CDR 90000 103"
  },
  {
    "starttime": "16:37",
    "artist": "Robert Schumann",
    "title": "Fünf Stücke im Volkston op.102",
    "time": "0:15:17",
    "composer": "Nicolas Altstaedt (cello) José Gallardo (piano)",
    "label": "Genuin GEN-10187"
  },
  {
    "starttime": "16:53",
    "artist": "Sergej Liapunov",
    "title": "12 Etudes d'exécution transcendante op.11: 5.Nuit d'été",
    "time": "0:06:35",
    "composer": "Florian Noack (piano)",
    "label": "La Dolce Volta LDV90"
  },
  {
    "starttime": "16:57",
    "artist": "Dan Forrest",
    "title": "Requiem for the Living",
    "time": "0:38:39",
    "composer": "Bel Canto Company o.l.v. Welborn Young",
    "label": "HINSHAW MUSIC, INC. "
  },
  {
    "starttime": "17:37",
    "artist": "Dirk Brossé",
    "title": "La Vida es un Sueno: El Sueno",
    "time": "0:05:21",
    "composer": "Claron McFadden (sopraan) London Philharmonic Orchestra o.l.v. Dirk Brossé",
    "label": "Philips 465 274-2"
  },
  {
    "starttime": "17:43",
    "artist": "Karel Mestdagh",
    "title": "Sechs neue Divertimenti in Walzerform op.10",
    "time": "0:08:29",
    "composer": "Jan Vande Weghe (piano)",
    "label": "SCB 1502"
  },
  {
    "starttime": "17:52",
    "artist": "Simeon Ten Holt",
    "title": "Canto Ostinato (voor 2 piano's en 2 marimba's): Slot",
    "time": "0:07:01",
    "composer": "Jeroen Van Veen (piano) Sandra Van Veen (piano) Peter Elbertse (marimba) Esther Doornink (marimba)",
    "label": "Piano Productions PP-2010"
  },
  {
    "starttime": "18:07",
    "artist": "Barry Manilow, Bruce Sussman, Jack Feldman",
    "title": "Copacabana",
    "time": "0:03:46",
    "composer": "Lucienne Renaudin-Vary (trompet) Ludwig Orchestra Berlage Saxophone Quartet",
    "label": "Alpha 790"
  },
  {
    "starttime": "18:11",
    "artist": "Irving Berlin",
    "title": "Sisters",
    "time": "0:03:06",
    "composer": "Marcella Puppini (zang) Kate Mullins (zang) Stephanie O'Brien (zang) Marcella Puppini (accordeon) Kate Mullins (melodica) Stephanie O'Brien (harp/melodica) Puppini Sisters",
    "label": "Universal Music 1706227"
  },
  {
    "starttime": "18:15",
    "artist": "José Razzano, Celedonio Flores, Hugo Diaz, Carlos Gardel",
    "title": "Mano a Mano",
    "time": "0:03:50",
    "composer": "Marius Ruhland",
    "label": "Milan 399 186-2"
  },
  {
    "starttime": "18:19",
    "artist": "J.B. Leonard",
    "title": "Mambo del amor",
    "time": "0:02:55",
    "composer": "Celia Cruz (zang)",
    "label": "Seeco Tropical STR-52051"
  },
  {
    "starttime": "18:22",
    "artist": "Electo Rosell 'Chepin'",
    "title": "Bodas de Oro",
    "time": "0:04:40",
    "composer": "Ry Cooder (gitaar) Manuel Galban (gitaar) Joachim Cooder (drums) Orlando 'Cachaito' Lopez (contrabas) Jim Keltner (drums)",
    "label": "WEA/Elektra/Nonesuch 7559-79691-2"
  },
  {
    "starttime": "18:27",
    "artist": "Cole Porter",
    "title": "The Wedding Cake Walk",
    "time": "0:02:33",
    "composer": "Fred Astaire (zang)",
    "label": "MCA M 18 769"
  },
  {
    "starttime": "18:30",
    "artist": "Richard Wagner",
    "title": "Wedding Boogie",
    "time": "0:02:47",
    "composer": "Harry Frekin En Orkest",
    "label": "Victory 9507"
  },
  {
    "starttime": "18:33",
    "artist": "Moisés Simons",
    "title": "The Peanut Vendor (El Manisero)",
    "time": "0:02:31",
    "composer": "Vince Giordano And The Nighthawks",
    "label": "Gardier "
  },
  {
    "starttime": "18:36",
    "artist": "Jacques Brel",
    "title": "La Valse à Mille Temps",
    "time": "0:05:02",
    "composer": "Filip Jordens",
    "label": "Toe TOE-981006"
  },
  {
    "starttime": "18:41",
    "artist": "Rony Verbiest",
    "title": "Bolero",
    "time": "0:04:25",
    "composer": "Rony Verbiest",
    "label": "VRT Opname "
  },
  {
    "starttime": "18:46",
    "artist": "Leighla Whipper",
    "title": "Back Down to the Tropics",
    "time": "0:03:55",
    "composer": "Charlie Rouse",
    "label": "EMI/Blue Note CDP-7955902"
  },
  {
    "starttime": "18:50",
    "artist": "John Sebastian",
    "title": "Daydream",
    "time": "0:03:06",
    "composer": "The Muppets",
    "label": "Jim Henson Records 74321-23338-2"
  },
  {
    "starttime": "18:54",
    "artist": "John Blackburn, Karl Suessdorf",
    "title": "Moonlight in Vermont",
    "time": "0:05:17",
    "composer": "DOROTHY ASHBY; FRANK WESS",
    "label": "Avid Entertainment "
  },
  {
    "starttime": "18:59",
    "artist": "Consuelo Velazquez",
    "title": "Besame Mucho",
    "time": "0:09:10",
    "composer": "Curtis Fuller (trombone) Jymie Merritt (contrabas) Zoot Sims (tenorsaxofoon) Dave Bailey (drums) Tommy Flanagan (piano) Curtis Fuller Quintet",
    "label": "Epic 25 8P-5113"
  },
  {
    "starttime": "19:09",
    "artist": "Antonio Carlos Jobim",
    "title": "A felicidade",
    "time": "0:03:28",
    "composer": "Agnès Jaoui (zang) Helena Noguerra (zang) Liat Cohen (klassieke gitaar)",
    "label": "Erato 08256 463503 5 3"
  },
  {
    "starttime": "19:13",
    "artist": "Clare Fischer",
    "title": "Samba da Borboleta",
    "time": "0:03:33",
    "composer": "Ralph Peña (contrabas) Larry Bunker (vibrafoon/drums)",
    "label": "Masterworks "
  },
  {
    "starttime": "19:17",
    "artist": "Gene Lees, Antonio Carlos Jobim",
    "title": "Quiet Nights of Quiet Stars (Corcovado)",
    "time": "0:02:53",
    "composer": "Blossom Dearie",
    "label": "EMI/Blue Note 50999-215999 2-7"
  },
  {
    "starttime": "19:20",
    "artist": "Bob Davidse, Al Van Dam",
    "title": "Karolientje",
    "time": "0:03:32",
    "composer": "Mandolinman",
    "label": "Majestic World MSRCD-005"
  },
  {
    "starttime": "19:24",
    "artist": "Lorenz Hart, Richard Rodgers",
    "title": "Little Girl Blue",
    "time": "0:05:39",
    "composer": "Hank Jones (piano) Wendell Marshall (contrabas) Kenny Clarke (drums) Hank Jones Trio",
    "label": "Fresh Sound Records "
  },
  {
    "starttime": "19:30",
    "artist": "Leo Robin, Ralph Rainger",
    "title": "Thanks for the Memory",
    "time": "0:07:00",
    "composer": "Sarah Vaughan (zang) Wendell Culley (trompet) Henry Coker (trombone) Frank Wess (tenorsaxofoon) Ronnell Bright (piano) Richard Davis (contrabas) Roy Haynes (drums)",
    "label": "Universal Records 0094635213225"
  },
  {
    "starttime": "19:37",
    "artist": "Anais Cruz",
    "title": "Mis dos Pequenas",
    "time": "0:04:06",
    "composer": "Dee Nasty (pick ups) Orlando 'Cachaito' Lopez (contrabas) Miguel Anga Diaz (conga/percussie) Amadito Valdés (timbales cubaines) Carlos Gonzalez (bongos) Alejandro Pichardo (rasp/claves) Bigga Morrison (Hammond orgel/clavinet) Manuel Galban (gitaar) Hugh M",
    "label": "World Circuit WCD-061"
  },
  {
    "starttime": "19:41",
    "artist": "Harald Kloser, Thomas Schobel",
    "title": "Comedian Harmonists",
    "time": "0:02:08",
    "composer": "Pasadena Roof Orchestra",
    "label": "EMI 7243-4 93146 2-7"
  },
  {
    "starttime": "19:44",
    "artist": "Johann Strauss",
    "title": "Perpetuum Mobile",
    "time": "0:02:24",
    "composer": "Comedian Harmonists",
    "label": "EPM Musique 983782"
  },
  {
    "starttime": "19:46",
    "artist": "Ford Dabney, Lew Brown, Cecil Mack",
    "title": "Piano Stomp (Shine)",
    "time": "0:02:57",
    "composer": "Cootie Williams (trompet) Lionel Hampton (zang) Lionel Hampton (vibrafoon/piano) Johnny Hodges (altsaxofoon) Allan Reuss (gitaar) Vido Musso (tenorsaxofoon) Art Rollini (tenorsaxofoon) Buster Bailey (klarinet) Cozy Cole (drums) Clyde Hart (piano) Jo Jones",
    "label": "RCA 74321-15525-2"
  },
  {
    "starttime": "19:49",
    "artist": "Bertolt Brecht, Kurt Weill",
    "title": "Nannas Lied",
    "time": "0:03:42",
    "composer": "Ute Lemper (zang) Rias-Ensemble",
    "label": "Decca 425 204-2"
  },
  {
    "starttime": "19:53",
    "artist": "Neal Hefti",
    "title": "Lil' Darlin'",
    "time": "0:03:45",
    "composer": "Joe Pass (gitaar) Eberhard Weber (contrabas) Kenny Clare (drums)",
    "label": "MPS POCJ-2508"
  },
  {
    "starttime": "19:57",
    "artist": "Stanley Turrentine",
    "title": "Sugar",
    "time": "0:10:02",
    "composer": "Stanley Turrentine",
    "label": "Epic 450952-2"
  },
  {
    "starttime": "20:00",
    "artist": "",
    "title": "",
    "time": "0:00:30",
    "composer": "",
    "label": ""
  },
  {
    "starttime": "20:01",
    "artist": "Johannes Brahms",
    "title": "Tragische ouverture, op. 81",
    "time": "0:13:07",
    "composer": "Berliner Philharmoniker",
    "label": "Deutsche Grammophon 429 765-2"
  },
  {
    "starttime": "20:15",
    "artist": "Ludwig Van Beethoven",
    "title": "Concerto voor piano en orkest nr. 5 in Es groot, op. 73 /Keizersconcerto/Emperor/Empereur",
    "time": "0:39:01",
    "composer": "Maurizio Pollini (piano) Berliner Philharmoniker",
    "label": "Deutsche Grammophon 477 7244"
  },
  {
    "starttime": "20:54",
    "artist": "Felix Mendelssohn Bartholdy",
    "title": "Ein Sommernachtstraum, op. 61: Delen uit Ein Sommernachtstraum, op. 61 (Toneelmuziek)",
    "time": "0:40:13",
    "composer": "Deborah York (sopraan) Stella Doufexis (mezzosopraan) Berliner Philharmoniker Chor Des Bayerischen Rundfunks o.l.v. Claudio Abbado",
    "label": "Berliner Philharmoniker Recordings 160081"
  },
  {
    "starttime": "21:35",
    "artist": "Frédéric Chopin",
    "title": "24 Preludes, op. 28",
    "time": "0:36:17",
    "composer": "Maurizio Pollini (piano)",
    "label": "Deutsche Grammophon 413 796-2"
  },
  {
    "starttime": "22:12",
    "artist": "Wolfgang Amadeus Mozart",
    "title": "Strijkkwintet nr. 4 in g klein, KV 516",
    "time": "0:33:19",
    "composer": "Nicolas Van Kuijk (viool) Sylvain Favre-Bulle (viool) Emmanuel François (altviool) François Robin (cello) Adrien La Marca (altviool) Quatuor Van Kuijk",
    "label": "Alpha 587"
  },
  {
    "starttime": "22:45",
    "artist": "Johann Sebastian Bach",
    "title": "Das wohltemperierte Klavier, boek 1: Prelude en fuga nr. 4 in cis klein, BWV 849",
    "time": "0:07:35",
    "composer": "Maurizio Pollini (piano)",
    "label": "Deutsche Grammophon 477 9529"
  },
  {
    "starttime": "22:54",
    "artist": "Anton Webern",
    "title": "Variaties voor piano, op. 27 /Variationen",
    "time": "0:05:58",
    "composer": "Maurizio Pollini (piano)",
    "label": "Deutsche Grammophon 477 9529"
  },
  {
    "starttime": "23:00",
    "artist": "Luigi Nono",
    "title": "...sofferte onde serene... (voor piano en band)",
    "time": "0:14:06",
    "composer": "Maurizio Pollini (piano)",
    "label": "Deutsche Grammophon 471 362-2"
  },
  {
    "starttime": "23:15",
    "artist": "Luigi Dallapiccola",
    "title": "Piccola musica notturna /Kleine nachtmuziek",
    "time": "0:09:00",
    "composer": "Bbc Philharmonic Orchestra",
    "label": "Chandos CHAN-10258"
  },
  {
    "starttime": "23:24",
    "artist": "Claude Debussy",
    "title": "Preludes voor piano, boek 1: V Les collines d'Anacapri (Très modéré)",
    "time": "0:02:51",
    "composer": "Maurizio Pollini (piano)",
    "label": "Deutsche Grammophon 445 187-2"
  },
  {
    "starttime": "23:27",
    "artist": "Claude Debussy",
    "title": "Preludes voor piano, boek 1: VI Des pas sur la neige (Triste et lent)",
    "time": "0:03:45",
    "composer": "Maurizio Pollini (piano)",
    "label": "Deutsche Grammophon 445 187-2"
  },
  {
    "starttime": "23:31",
    "artist": "Claude Debussy",
    "title": "Preludes voor piano, boek 1: VII Ce qu'a vu le vent d'ouest (Animé et tumultueux)",
    "time": "0:03:06",
    "composer": "Maurizio Pollini (piano)",
    "label": "Deutsche Grammophon 445 187-2"
  },
  {
    "starttime": "23:34",
    "artist": "Claude Debussy",
    "title": "Preludes voor piano, boek 1: VIII La fille aux cheveux de lin (Très calme et doucement expressif)",
    "time": "0:02:27",
    "composer": "Maurizio Pollini (piano)",
    "label": "Deutsche Grammophon 445 187-2"
  },
  {
    "starttime": "23:36",
    "artist": "Claude Debussy",
    "title": "Preludes voor piano, boek 1: IX La sérénade interrompue (modérément animé)",
    "time": "0:02:27",
    "composer": "Maurizio Pollini (piano)",
    "label": "Deutsche Grammophon 445 187-2"
  },
  {
    "starttime": "23:39",
    "artist": "Camille Saint-Saëns",
    "title": "Introductie en Rondo Capriccioso in a klein, op. 28 (voor viool en orkest)",
    "time": "0:09:22",
    "composer": "Deborah Nemtanu (viool) Orchestre De Chambre De Paris o.l.v. Thomas Zehetmair",
    "label": "Mirare MIR-193"
  },
  {
    "starttime": "23:49",
    "artist": "César Franck",
    "title": "Symfonie in d klein, op. 48: II Allegretto",
    "time": "0:09:48",
    "composer": "Orchestre Des Champs Elysees",
    "label": "Harmonia Mundi HMC-901771"
  },
  {
    "starttime": "23:59",
    "artist": "César Franck",
    "title": "Symfonie in d klein, op. 48: III Allegro non troppo",
    "time": "0:10:11",
    "composer": "Orchestre Des Champs Elysees",
    "label": "Harmonia Mundi HMC-901771"
  }
]